firstaid/__init__.py
firstaid/docx.py
firstaid/pptx.py
firstaid-0.0.1.dist-info/DESCRIPTION.rst
firstaid-0.0.1.dist-info/METADATA
firstaid-0.0.1.dist-info/RECORD
firstaid-0.0.1.dist-info/WHEEL
firstaid-0.0.1.dist-info/metadata.json
firstaid-0.0.1.dist-info/top_level.txt
