Metadata-Version: 2.0
Name: firstaid
Version: 0.0.1
Summary: A First-Aid for Data Analysis and Reporting
Home-page: UNKNOWN
Author: QuantLab inc.
Author-email: yu@mindscale.kr
License: UNKNOWN
Platform: UNKNOWN
Requires-Dist: pandas
Requires-Dist: Pillow
Requires-Dist: python-pptx
Requires-Dist: python-docx
